README.md
setup.cfg
setup.py
NM_LFAK/__init__.py
NM_LFAK.egg-info/PKG-INFO
NM_LFAK.egg-info/SOURCES.txt
NM_LFAK.egg-info/dependency_links.txt
NM_LFAK.egg-info/not-zip-safe
NM_LFAK.egg-info/requires.txt
NM_LFAK.egg-info/top_level.txt
NM_LFAK/annealing/__init__.py
NM_LFAK/annealing/main.py
NM_LFAK/diffint/__init__.py
NM_LFAK/diffint/main.py
NM_LFAK/fourwave/__init__.py
NM_LFAK/fourwave/main.py
NM_LFAK/interp1d/__init__.py
NM_LFAK/interp1d/main.py
NM_LFAK/matrix/ComplexFraction.py
NM_LFAK/matrix/Fraction.py
NM_LFAK/matrix/Matrix.py
NM_LFAK/matrix/SparseMatrix.py
NM_LFAK/matrix/Symbol.py
NM_LFAK/matrix/__init__.py
NM_LFAK/odu/__init__.py
NM_LFAK/odu/main.py