Metadata-Version: 1.0
Name: NM-LFAK
Version: 1.2
Summary: Numerical methods
Home-page: UNKNOWN
Author: UNKNOWN
Author-email: vovalagutov1111@yandex.ru
License: UNKNOWN
Platform: UNKNOWN
